PasteDeploy-3.0.1-py3.10-nspkg.pth
paste/deploy/__init__.py
paste/deploy/config.py
paste/deploy/converters.py
paste/deploy/loadwsgi.py
paste/deploy/paster_templates.py
paste/deploy/util.py
paste/deploy/paster_templates/paste_deploy/+package+/sampleapp.py_tmpl
paste/deploy/paster_templates/paste_deploy/+package+/wsgiapp.py_tmpl
paste/deploy/paster_templates/paste_deploy/docs/devel_config.ini_tmpl
PasteDeploy-3.0.1.dist-info/METADATA
PasteDeploy-3.0.1.dist-info/WHEEL
PasteDeploy-3.0.1.dist-info/entry_points.txt
PasteDeploy-3.0.1.dist-info/namespace_packages.txt
PasteDeploy-3.0.1.dist-info/top_level.txt
PasteDeploy-3.0.1.dist-info/RECORD
